workbench/__init__.py
workbench/cli.py
workbench/executor.py
workbench/prediction/__init__.py
workbench/prediction/constants.py
workbench/prediction/model_builder.py
workbench/prediction/model_deployer.py
workbench/prediction/notebook_model_builder.py
workbench/prediction/container/Dockerfile
workbench/prediction/container/__init__.py
workbench/prediction/container/app.py
workbench/prediction/container/prediction.py
workbench/prediction/container/requirements.txt
ai_workbench-1.2.0.dist-info/LICENSE
ai_workbench-1.2.0.dist-info/METADATA
ai_workbench-1.2.0.dist-info/WHEEL
ai_workbench-1.2.0.dist-info/entry_points.txt
ai_workbench-1.2.0.dist-info/top_level.txt
ai_workbench-1.2.0.dist-info/RECORD
